{
   "packages":[
      {
         "name":"AntBlePlatform",
         "maintainer":"ALeibbrandt",
         "websiteURL":"http://www.skipass.com",
         "email":"a.leib@citycable.ch",
         "help":{
            "online":"http://www.skipass.com"
         },
         "platforms":[
            {
               "name": "ANT BLE Platform Boards",
               "architecture": "AntBlePlatformA",
               "version": "1.0.0",
               "category": "AntBlePlatform",
               "url": "https://polybox.ethz.ch/index.php/s/t8UPKe56h3Ltvqa/download",
               "archiveFileName": "AntBlePlatform.zip",
               "checksum": "SHA-256:C7ABE35DA97468ECA345C53AD248A85843845E96448293D437D62B8C51ED8C1A",
               "size": "6610944",
               "help":{
                  "online":"http://www.skipass.com"
               },
               "boards": [
                  {
                     "name": "AntBlePlatformA"
                  }
               ],
               "toolsDependencies": [
                  {
                     "packager": "AntBlePlatform",
                     "name": "arm-none-eabi-gcc",
                     "version": "4.8.3-2014q1"
                  }
               ]
            }
         ],
      	"tools":[
            {
               "name":"arm-none-eabi-gcc",
               "version":"4.8.3-2014q1",
               "systems":[
                  {
                     "host":"i686-mingw32",
                     "archiveFileName":"gcc-arm-none-eabi-4.8.3-2014q1-windows.tar.gz",
                     "url":"http://downloads.arduino.cc/gcc-arm-none-eabi-4.8.3-2014q1-windows.tar.gz",
                     "checksum":"SHA-256:fd8c111c861144f932728e00abd3f7d1107e186eb9cd6083a54c7236ea78b7c2",
                     "size":"84537449"
                  }
               ]
            }
         ]
      }
   ]
}
